scrapper/__init__.py
scrapper/data_scrapper.py
scrapper/supreme_court_spain.py
scrapper/supreme_court_united_states.py
lawLib-0.5.1.dist-info/LICENSE
lawLib-0.5.1.dist-info/METADATA
lawLib-0.5.1.dist-info/WHEEL
lawLib-0.5.1.dist-info/top_level.txt
lawLib-0.5.1.dist-info/RECORD
