Metadata-Version: 2.1
Name: lawLib
Version: 0.5.1
Summary: Library to extract legal information from official resources
Home-page: https://github.com/JonanOribe/lawLib
Author: Jon Ander Oribe
Author-email: jonan.oribe@gmail.com
License: MIT
Platform: UNKNOWN
Classifier: Intended Audience :: Developers
Classifier: License :: OSI Approved :: MIT License
Classifier: Programming Language :: Python
Classifier: Programming Language :: Python :: 3
Classifier: Programming Language :: Python :: 3.6
Classifier: Programming Language :: Python :: 3.7
Classifier: Programming Language :: Python :: 3.8
Classifier: Programming Language :: Python :: 3.9
Classifier: Operating System :: OS Independent
License-File: LICENSE
Requires-Dist: requests
